conversionutil/__init__.py
conversionutil/_metadata.py
conversionutil/convert.py
conversionutil/date_and_time_conversions.py
conversionutil/dx.py
conversionutil/ex.py
conversionutil/excel_to_json.py
conversionutil/modify.py
conversionutil/storage.py
conversionutil/text/__init__.py
conversionutil/text/asciify.py
conversionutil/text/fullwidth.py
conversionutil/unittests/__init__.py
conversionutil/unittests/test_convert.py
conversionutil/unittests/test_excel_to_json.py
conversionutil-1.4.6.dist-info/LICENSE.txt
conversionutil-1.4.6.dist-info/METADATA
conversionutil-1.4.6.dist-info/WHEEL
conversionutil-1.4.6.dist-info/entry_points.txt
conversionutil-1.4.6.dist-info/top_level.txt
conversionutil-1.4.6.dist-info/RECORD
