Metadata-Version: 2.1
Name: conversionutil
Version: 1.4.6
Summary: A collection of conversion utilities.
Home-page: https://bitbucket.org/daycoder/conversionutil.git
Author: Hywel Thomas
Author-email: hywel.thomas@mac.com
License: MIT
Download-URL: https://bitbucket.org/daycoder/conversionutil.git/get/1.4.6.tar
Keywords: convert
Platform: UNKNOWN
Classifier: Development Status :: 3 - Alpha
Classifier: Intended Audience :: Developers
Classifier: License :: OSI Approved :: MIT License
Classifier: Programming Language :: Python :: 2
Classifier: Programming Language :: Python :: 2.7
Classifier: Programming Language :: Python :: 3
Classifier: Programming Language :: Python :: 3.6
Classifier: Topic :: Utilities
Requires-Dist: pip (>=18.1)
Requires-Dist: future (>=0.16.0)
Requires-Dist: logging-helper (>=1.8.5)
Requires-Dist: timingsutil (>=1.5.1)
Requires-Dist: openpyxl (>=2.4.4)
Provides-Extra: test
